my_numpy/__init__.py
my_numpy/stats.py
my_numpy-0.1.4.dist-info/METADATA
my_numpy-0.1.4.dist-info/WHEEL
my_numpy-0.1.4.dist-info/RECORD
