Metadata-Version: 2.1
Name: my-numpy
Version: 0.1.4
Summary: 
Author: Ramesh Doddi
Author-email: rdoddi.pro@gmail.com
Requires-Python: >=3.13,<4.0
Classifier: Programming Language :: Python :: 3
Classifier: Programming Language :: Python :: 3.13
Requires-Dist: numpy (>=2.1.3,<3.0.0)
